amazon_selenium/__init__.py
amazon_selenium/amazon.py
amazon_selenium-0.1.2.dist-info/METADATA
amazon_selenium-0.1.2.dist-info/WHEEL
amazon_selenium-0.1.2.dist-info/top_level.txt
amazon_selenium-0.1.2.dist-info/RECORD
