Metadata-Version: 2.1
Name: amazon-selenium
Version: 0.1.2
Summary: amazon_selenium
Home-page: https://github.com/kkristof200/amazon_selenium
Author: Kovács Kristóf-Attila
License: UNKNOWN
Platform: UNKNOWN
Classifier: Programming Language :: Python :: 3
Classifier: License :: OSI Approved :: MIT License
Classifier: Operating System :: OS Independent
Requires-Python: >=3.6
Requires-Dist: selenium-firefox
Requires-Dist: kov-utils
